{
  "total_count": 200641,
  "incomplete_results": false,
  "items": [
    {
      "id": 1828795,
      "name": "AFNetworking",
      "full_name": "AFNetworking/AFNetworking",
      "owner": {
        "login": "AFNetworking",
        "id": 1181541,
        "avatar_url": "https://avatars.githubusercontent.com/u/1181541?v=3",
        "gravatar_id": "",
        "url": "https://api.github.com/users/AFNetworking",
        "html_url": "https://github.com/AFNetworking",
        "followers_url": "https://api.github.com/users/AFNetworking/followers",
        "following_url": "https://api.github.com/users/AFNetworking/following{/other_user}",
        "gists_url": "https://api.github.com/users/AFNetworking/gists{/gist_id}",
        "starred_url": "https://api.github.com/users/AFNetworking/starred{/owner}{/repo}",
        "subscriptions_url": "https://api.github.com/users/AFNetworking/subscriptions",
        "organizations_url": "https://api.github.com/users/AFNetworking/orgs",
        "repos_url": "https://api.github.com/users/AFNetworking/repos",
        "events_url": "https://api.github.com/users/AFNetworking/events{/privacy}",
        "received_events_url": "https://api.github.com/users/AFNetworking/received_events",
        "type": "Organization",
        "site_admin": false
      },
      "private": false,
      "html_url": "https://github.com/AFNetworking/AFNetworking",
      "description": "A delightful iOS and OS X networking framework",
      "fork": false,
      "url": "https://api.github.com/repos/AFNetworking/AFNetworking",
      "forks_url": "https://api.github.com/repos/AFNetworking/AFNetworking/forks",
      "keys_url": "https://api.github.com/repos/AFNetworking/AFNetworking/keys{/key_id}",
      "collaborators_url": "https://api.github.com/repos/AFNetworking/AFNetworking/collaborators{/collaborator}",
      "teams_url": "https://api.github.com/repos/AFNetworking/AFNetworking/teams",
      "hooks_url": "https://api.github.com/repos/AFNetworking/AFNetworking/hooks",
      "issue_events_url": "https://api.github.com/repos/AFNetworking/AFNetworking/issues/events{/number}",
      "events_url": "https://api.github.com/repos/AFNetworking/AFNetworking/events",
      "assignees_url": "https://api.github.com/repos/AFNetworking/AFNetworking/assignees{/user}",
      "branches_url": "https://api.github.com/repos/AFNetworking/AFNetworking/branches{/branch}",
      "tags_url": "https://api.github.com/repos/AFNetworking/AFNetworking/tags",
      "blobs_url": "https://api.github.com/repos/AFNetworking/AFNetworking/git/blobs{/sha}",
      "git_tags_url": "https://api.github.com/repos/AFNetworking/AFNetworking/git/tags{/sha}",
      "git_refs_url": "https://api.github.com/repos/AFNetworking/AFNetworking/git/refs{/sha}",
      "trees_url": "https://api.github.com/repos/AFNetworking/AFNetworking/git/trees{/sha}",
      "statuses_url": "https://api.github.com/repos/AFNetworking/AFNetworking/statuses/{sha}",
      "languages_url": "https://api.github.com/repos/AFNetworking/AFNetworking/languages",
      "stargazers_url": "https://api.github.com/repos/AFNetworking/AFNetworking/stargazers",
      "contributors_url": "https://api.github.com/repos/AFNetworking/AFNetworking/contributors",
      "subscribers_url": "https://api.github.com/repos/AFNetworking/AFNetworking/subscribers",
      "subscription_url": "https://api.github.com/repos/AFNetworking/AFNetworking/subscription",
      "commits_url": "https://api.github.com/repos/AFNetworking/AFNetworking/commits{/sha}",
      "git_commits_url": "https://api.github.com/repos/AFNetworking/AFNetworking/git/commits{/sha}",
      "comments_url": "https://api.github.com/repos/AFNetworking/AFNetworking/comments{/number}",
      "issue_comment_url": "https://api.github.com/repos/AFNetworking/AFNetworking/issues/comments{/number}",
      "contents_url": "https://api.github.com/repos/AFNetworking/AFNetworking/contents/{+path}",
      "compare_url": "https://api.github.com/repos/AFNetworking/AFNetworking/compare/{base}...{head}",
      "merges_url": "https://api.github.com/repos/AFNetworking/AFNetworking/merges",
      "archive_url": "https://api.github.com/repos/AFNetworking/AFNetworking/{archive_format}{/ref}",
      "downloads_url": "https://api.github.com/repos/AFNetworking/AFNetworking/downloads",
      "issues_url": "https://api.github.com/repos/AFNetworking/AFNetworking/issues{/number}",
      "pulls_url": "https://api.github.com/repos/AFNetworking/AFNetworking/pulls{/number}",
      "milestones_url": "https://api.github.com/repos/AFNetworking/AFNetworking/milestones{/number}",
      "notifications_url": "https://api.github.com/repos/AFNetworking/AFNetworking/notifications{?since,all,participating}",
      "labels_url": "https://api.github.com/repos/AFNetworking/AFNetworking/labels{/name}",
      "releases_url": "https://api.github.com/repos/AFNetworking/AFNetworking/releases{/id}",
      "created_at": "2011-05-31T21:28:44Z",
      "updated_at": "2015-05-09T15:54:44Z",
      "pushed_at": "2015-05-08T15:36:30Z",
      "git_url": "git://github.com/AFNetworking/AFNetworking.git",
      "ssh_url": "git@github.com:AFNetworking/AFNetworking.git",
      "clone_url": "https://github.com/AFNetworking/AFNetworking.git",
      "svn_url": "https://github.com/AFNetworking/AFNetworking",
      "homepage": "http://afnetworking.com",
      "size": 15194,
      "stargazers_count": 17318,
      "watchers_count": 17318,
      "language": "Objective-C",
      "has_issues": true,
      "has_downloads": true,
      "has_wiki": true,
      "has_pages": false,
      "forks_count": 5054,
      "mirror_url": null,
      "open_issues_count": 41,
      "forks": 5054,
      "open_issues": 41,
      "watchers": 17318,
      "default_branch": "master",
      "score": 1.0
    },
    {
      "id": 313419,
      "name": "SDWebImage",
      "full_name": "rs/SDWebImage",
      "owner": {
        "login": "rs",
        "id": 68232,
        "avatar_url": "https://avatars.githubusercontent.com/u/68232?v=3",
        "gravatar_id": "",
        "url": "https://api.github.com/users/rs",
        "html_url": "https://github.com/rs",
        "followers_url": "https://api.github.com/users/rs/followers",
        "following_url": "https://api.github.com/users/rs/following{/other_user}",
        "gists_url": "https://api.github.com/users/rs/gists{/gist_id}",
        "starred_url": "https://api.github.com/users/rs/starred{/owner}{/repo}",
        "subscriptions_url": "https://api.github.com/users/rs/subscriptions",
        "organizations_url": "https://api.github.com/users/rs/orgs",
        "repos_url": "https://api.github.com/users/rs/repos",
        "events_url": "https://api.github.com/users/rs/events{/privacy}",
        "received_events_url": "https://api.github.com/users/rs/received_events",
        "type": "User",
        "site_admin": false
      },
      "private": false,
      "html_url": "https://github.com/rs/SDWebImage",
      "description": "Asynchronous image downloader with cache support with an UIImageView category",
      "fork": false,
      "url": "https://api.github.com/repos/rs/SDWebImage",
      "forks_url": "https://api.github.com/repos/rs/SDWebImage/forks",
      "keys_url": "https://api.github.com/repos/rs/SDWebImage/keys{/key_id}",
      "collaborators_url": "https://api.github.com/repos/rs/SDWebImage/collaborators{/collaborator}",
      "teams_url": "https://api.github.com/repos/rs/SDWebImage/teams",
      "hooks_url": "https://api.github.com/repos/rs/SDWebImage/hooks",
      "issue_events_url": "https://api.github.com/repos/rs/SDWebImage/issues/events{/number}",
      "events_url": "https://api.github.com/repos/rs/SDWebImage/events",
      "assignees_url": "https://api.github.com/repos/rs/SDWebImage/assignees{/user}",
      "branches_url": "https://api.github.com/repos/rs/SDWebImage/branches{/branch}",
      "tags_url": "https://api.github.com/repos/rs/SDWebImage/tags",
      "blobs_url": "https://api.github.com/repos/rs/SDWebImage/git/blobs{/sha}",
      "git_tags_url": "https://api.github.com/repos/rs/SDWebImage/git/tags{/sha}",
      "git_refs_url": "https://api.github.com/repos/rs/SDWebImage/git/refs{/sha}",
      "trees_url": "https://api.github.com/repos/rs/SDWebImage/git/trees{/sha}",
      "statuses_url": "https://api.github.com/repos/rs/SDWebImage/statuses/{sha}",
      "languages_url": "https://api.github.com/repos/rs/SDWebImage/languages",
      "stargazers_url": "https://api.github.com/repos/rs/SDWebImage/stargazers",
      "contributors_url": "https://api.github.com/repos/rs/SDWebImage/contributors",
      "subscribers_url": "https://api.github.com/repos/rs/SDWebImage/subscribers",
      "subscription_url": "https://api.github.com/repos/rs/SDWebImage/subscription",
      "commits_url": "https://api.github.com/repos/rs/SDWebImage/commits{/sha}",
      "git_commits_url": "https://api.github.com/repos/rs/SDWebImage/git/commits{/sha}",
      "comments_url": "https://api.github.com/repos/rs/SDWebImage/comments{/number}",
      "issue_comment_url": "https://api.github.com/repos/rs/SDWebImage/issues/comments{/number}",
      "contents_url": "https://api.github.com/repos/rs/SDWebImage/contents/{+path}",
      "compare_url": "https://api.github.com/repos/rs/SDWebImage/compare/{base}...{head}",
      "merges_url": "https://api.github.com/repos/rs/SDWebImage/merges",
      "archive_url": "https://api.github.com/repos/rs/SDWebImage/{archive_format}{/ref}",
      "downloads_url": "https://api.github.com/repos/rs/SDWebImage/downloads",
      "issues_url": "https://api.github.com/repos/rs/SDWebImage/issues{/number}",
      "pulls_url": "https://api.github.com/repos/rs/SDWebImage/pulls{/number}",
      "milestones_url": "https://api.github.com/repos/rs/SDWebImage/milestones{/number}",
      "notifications_url": "https://api.github.com/repos/rs/SDWebImage/notifications{?since,all,participating}",
      "labels_url": "https://api.github.com/repos/rs/SDWebImage/labels{/name}",
      "releases_url": "https://api.github.com/repos/rs/SDWebImage/releases{/id}",
      "created_at": "2009-09-21T17:39:19Z",
      "updated_at": "2015-05-09T16:09:13Z",
      "pushed_at": "2015-05-08T00:00:15Z",
      "git_url": "git://github.com/rs/SDWebImage.git",
      "ssh_url": "git@github.com:rs/SDWebImage.git",
      "clone_url": "https://github.com/rs/SDWebImage.git",
      "svn_url": "https://github.com/rs/SDWebImage",
      "homepage": "http://hackemist.com/SDWebImage/doc",
      "size": 8218,
      "stargazers_count": 8845,
      "watchers_count": 8845,
      "language": "Objective-C",
      "has_issues": true,
      "has_downloads": true,
      "has_wiki": true,
      "has_pages": false,
      "forks_count": 2458,
      "mirror_url": null,
      "open_issues_count": 126,
      "forks": 2458,
      "open_issues": 126,
      "watchers": 8845,
      "default_branch": "master",
      "score": 1.0
    },
    {
      "id": 3431083,
      "name": "GPUImage",
      "full_name": "BradLarson/GPUImage",
      "owner": {
        "login": "BradLarson",
        "id": 954279,
        "avatar_url": "https://avatars.githubusercontent.com/u/954279?v=3",
        "gravatar_id": "",
        "url": "https://api.github.com/users/BradLarson",
        "html_url": "https://github.com/BradLarson",
        "followers_url": "https://api.github.com/users/BradLarson/followers",
        "following_url": "https://api.github.com/users/BradLarson/following{/other_user}",
        "gists_url": "https://api.github.com/users/BradLarson/gists{/gist_id}",
        "starred_url": "https://api.github.com/users/BradLarson/starred{/owner}{/repo}",
        "subscriptions_url": "https://api.github.com/users/BradLarson/subscriptions",
        "organizations_url": "https://api.github.com/users/BradLarson/orgs",
        "repos_url": "https://api.github.com/users/BradLarson/repos",
        "events_url": "https://api.github.com/users/BradLarson/events{/privacy}",
        "received_events_url": "https://api.github.com/users/BradLarson/received_events",
        "type": "User",
        "site_admin": false
      },
      "private": false,
      "html_url": "https://github.com/BradLarson/GPUImage",
      "description": "An open source iOS framework for GPU-based image and video processing",
      "fork": false,
      "url": "https://api.github.com/repos/BradLarson/GPUImage",
      "forks_url": "https://api.github.com/repos/BradLarson/GPUImage/forks",
      "keys_url": "https://api.github.com/repos/BradLarson/GPUImage/keys{/key_id}",
      "collaborators_url": "https://api.github.com/repos/BradLarson/GPUImage/collaborators{/collaborator}",
      "teams_url": "https://api.github.com/repos/BradLarson/GPUImage/teams",
      "hooks_url": "https://api.github.com/repos/BradLarson/GPUImage/hooks",
      "issue_events_url": "https://api.github.com/repos/BradLarson/GPUImage/issues/events{/number}",
      "events_url": "https://api.github.com/repos/BradLarson/GPUImage/events",
      "assignees_url": "https://api.github.com/repos/BradLarson/GPUImage/assignees{/user}",
      "branches_url": "https://api.github.com/repos/BradLarson/GPUImage/branches{/branch}",
      "tags_url": "https://api.github.com/repos/BradLarson/GPUImage/tags",
      "blobs_url": "https://api.github.com/repos/BradLarson/GPUImage/git/blobs{/sha}",
      "git_tags_url": "https://api.github.com/repos/BradLarson/GPUImage/git/tags{/sha}",
      "git_refs_url": "https://api.github.com/repos/BradLarson/GPUImage/git/refs{/sha}",
      "trees_url": "https://api.github.com/repos/BradLarson/GPUImage/git/trees{/sha}",
      "statuses_url": "https://api.github.com/repos/BradLarson/GPUImage/statuses/{sha}",
      "languages_url": "https://api.github.com/repos/BradLarson/GPUImage/languages",
      "stargazers_url": "https://api.github.com/repos/BradLarson/GPUImage/stargazers",
      "contributors_url": "https://api.github.com/repos/BradLarson/GPUImage/contributors",
      "subscribers_url": "https://api.github.com/repos/BradLarson/GPUImage/subscribers",
      "subscription_url": "https://api.github.com/repos/BradLarson/GPUImage/subscription",
      "commits_url": "https://api.github.com/repos/BradLarson/GPUImage/commits{/sha}",
      "git_commits_url": "https://api.github.com/repos/BradLarson/GPUImage/git/commits{/sha}",
      "comments_url": "https://api.github.com/repos/BradLarson/GPUImage/comments{/number}",
      "issue_comment_url": "https://api.github.com/repos/BradLarson/GPUImage/issues/comments{/number}",
      "contents_url": "https://api.github.com/repos/BradLarson/GPUImage/contents/{+path}",
      "compare_url": "https://api.github.com/repos/BradLarson/GPUImage/compare/{base}...{head}",
      "merges_url": "https://api.github.com/repos/BradLarson/GPUImage/merges",
      "archive_url": "https://api.github.com/repos/BradLarson/GPUImage/{archive_format}{/ref}",
      "downloads_url": "https://api.github.com/repos/BradLarson/GPUImage/downloads",
      "issues_url": "https://api.github.com/repos/BradLarson/GPUImage/issues{/number}",
      "pulls_url": "https://api.github.com/repos/BradLarson/GPUImage/pulls{/number}",
      "milestones_url": "https://api.github.com/repos/BradLarson/GPUImage/milestones{/number}",
      "notifications_url": "https://api.github.com/repos/BradLarson/GPUImage/notifications{?since,all,participating}",
      "labels_url": "https://api.github.com/repos/BradLarson/GPUImage/labels{/name}",
      "releases_url": "https://api.github.com/repos/BradLarson/GPUImage/releases{/id}",
      "created_at": "2012-02-13T15:20:02Z",
      "updated_at": "2015-05-09T13:55:19Z",
      "pushed_at": "2015-05-06T15:48:45Z",
      "git_url": "git://github.com/BradLarson/GPUImage.git",
      "ssh_url": "git@github.com:BradLarson/GPUImage.git",
      "clone_url": "https://github.com/BradLarson/GPUImage.git",
      "svn_url": "https://github.com/BradLarson/GPUImage",
      "homepage": "http://www.sunsetlakesoftware.com/2012/02/12/introducing-gpuimage-framework",
      "size": 46706,
      "stargazers_count": 8701,
      "watchers_count": 8701,
      "language": "Objective-C",
      "has_issues": true,
      "has_downloads": true,
      "has_wiki": true,
      "has_pages": false,
      "forks_count": 2112,
      "mirror_url": null,
      "open_issues_count": 623,
      "forks": 2112,
      "open_issues": 623,
      "watchers": 8701,
      "default_branch": "master",
      "score": 1.0
    },
    {
      "id": 3606624,
      "name": "ReactiveCocoa",
      "full_name": "ReactiveCocoa/ReactiveCocoa",
      "owner": {
        "login": "ReactiveCocoa",
        "id": 3422977,
        "avatar_url": "https://avatars.githubusercontent.com/u/3422977?v=3",
        "gravatar_id": "",
        "url": "https://api.github.com/users/ReactiveCocoa",
        "html_url": "https://github.com/ReactiveCocoa",
        "followers_url": "https://api.github.com/users/ReactiveCocoa/followers",
        "following_url": "https://api.github.com/users/ReactiveCocoa/following{/other_user}",
        "gists_url": "https://api.github.com/users/ReactiveCocoa/gists{/gist_id}",
        "starred_url": "https://api.github.com/users/ReactiveCocoa/starred{/owner}{/repo}",
        "subscriptions_url": "https://api.github.com/users/ReactiveCocoa/subscriptions",
        "organizations_url": "https://api.github.com/users/ReactiveCocoa/orgs",
        "repos_url": "https://api.github.com/users/ReactiveCocoa/repos",
        "events_url": "https://api.github.com/users/ReactiveCocoa/events{/privacy}",
        "received_events_url": "https://api.github.com/users/ReactiveCocoa/received_events",
        "type": "Organization",
        "site_admin": false
      },
      "private": false,
      "html_url": "https://github.com/ReactiveCocoa/ReactiveCocoa",
      "description": "A framework for composing and transforming streams of values",
      "fork": false,
      "url": "https://api.github.com/repos/ReactiveCocoa/ReactiveCocoa",
      "forks_url": "https://api.github.com/repos/ReactiveCocoa/ReactiveCocoa/forks",
      "keys_url": "https://api.github.com/repos/ReactiveCocoa/ReactiveCocoa/keys{/key_id}",
      "collaborators_url": "https://api.github.com/repos/ReactiveCocoa/ReactiveCocoa/collaborators{/collaborator}",
      "teams_url": "https://api.github.com/repos/ReactiveCocoa/ReactiveCocoa/teams",
      "hooks_url": "https://api.github.com/repos/ReactiveCocoa/ReactiveCocoa/hooks",
      "issue_events_url": "https://api.github.com/repos/ReactiveCocoa/ReactiveCocoa/issues/events{/number}",
      "events_url": "https://api.github.com/repos/ReactiveCocoa/ReactiveCocoa/events",
      "assignees_url": "https://api.github.com/repos/ReactiveCocoa/ReactiveCocoa/assignees{/user}",
      "branches_url": "https://api.github.com/repos/ReactiveCocoa/ReactiveCocoa/branches{/branch}",
      "tags_url": "https://api.github.com/repos/ReactiveCocoa/ReactiveCocoa/tags",
      "blobs_url": "https://api.github.com/repos/ReactiveCocoa/ReactiveCocoa/git/blobs{/sha}",
      "git_tags_url": "https://api.github.com/repos/ReactiveCocoa/ReactiveCocoa/git/tags{/sha}",
      "git_refs_url": "https://api.github.com/repos/ReactiveCocoa/ReactiveCocoa/git/refs{/sha}",
      "trees_url": "https://api.github.com/repos/ReactiveCocoa/ReactiveCocoa/git/trees{/sha}",
      "statuses_url": "https://api.github.com/repos/ReactiveCocoa/ReactiveCocoa/statuses/{sha}",
      "languages_url": "https://api.github.com/repos/ReactiveCocoa/ReactiveCocoa/languages",
      "stargazers_url": "https://api.github.com/repos/ReactiveCocoa/ReactiveCocoa/stargazers",
      "contributors_url": "https://api.github.com/repos/ReactiveCocoa/ReactiveCocoa/contributors",
      "subscribers_url": "https://api.github.com/repos/ReactiveCocoa/ReactiveCocoa/subscribers",
      "subscription_url": "https://api.github.com/repos/ReactiveCocoa/ReactiveCocoa/subscription",
      "commits_url": "https://api.github.com/repos/ReactiveCocoa/ReactiveCocoa/commits{/sha}",
      "git_commits_url": "https://api.github.com/repos/ReactiveCocoa/ReactiveCocoa/git/commits{/sha}",
      "comments_url": "https://api.github.com/repos/ReactiveCocoa/ReactiveCocoa/comments{/number}",
      "issue_comment_url": "https://api.github.com/repos/ReactiveCocoa/ReactiveCocoa/issues/comments{/number}",
      "contents_url": "https://api.github.com/repos/ReactiveCocoa/ReactiveCocoa/contents/{+path}",
      "compare_url": "https://api.github.com/repos/ReactiveCocoa/ReactiveCocoa/compare/{base}...{head}",
      "merges_url": "https://api.github.com/repos/ReactiveCocoa/ReactiveCocoa/merges",
      "archive_url": "https://api.github.com/repos/ReactiveCocoa/ReactiveCocoa/{archive_format}{/ref}",
      "downloads_url": "https://api.github.com/repos/ReactiveCocoa/ReactiveCocoa/downloads",
      "issues_url": "https://api.github.com/repos/ReactiveCocoa/ReactiveCocoa/issues{/number}",
      "pulls_url": "https://api.github.com/repos/ReactiveCocoa/ReactiveCocoa/pulls{/number}",
      "milestones_url": "https://api.github.com/repos/ReactiveCocoa/ReactiveCocoa/milestones{/number}",
      "notifications_url": "https://api.github.com/repos/ReactiveCocoa/ReactiveCocoa/notifications{?since,all,participating}",
      "labels_url": "https://api.github.com/repos/ReactiveCocoa/ReactiveCocoa/labels{/name}",
      "releases_url": "https://api.github.com/repos/ReactiveCocoa/ReactiveCocoa/releases{/id}",
      "created_at": "2012-03-02T22:11:24Z",
      "updated_at": "2015-05-09T15:45:58Z",
      "pushed_at": "2015-05-09T15:26:32Z",
      "git_url": "git://github.com/ReactiveCocoa/ReactiveCocoa.git",
      "ssh_url": "git@github.com:ReactiveCocoa/ReactiveCocoa.git",
      "clone_url": "https://github.com/ReactiveCocoa/ReactiveCocoa.git",
      "svn_url": "https://github.com/ReactiveCocoa/ReactiveCocoa",
      "homepage": "",
      "size": 28869,
      "stargazers_count": 8069,
      "watchers_count": 8069,
      "language": "Objective-C",
      "has_issues": true,
      "has_downloads": true,
      "has_wiki": false,
      "has_pages": false,
      "forks_count": 1193,
      "mirror_url": null,
      "open_issues_count": 106,
      "forks": 1193,
      "open_issues": 106,
      "watchers": 8069,
      "default_branch": "swift-development",
      "score": 1.0
    },
    {
      "id": 508845,
      "name": "RestKit",
      "full_name": "RestKit/RestKit",
      "owner": {
        "login": "RestKit",
        "id": 903233,
        "avatar_url": "https://avatars.githubusercontent.com/u/903233?v=3",
        "gravatar_id": "",
        "url": "https://api.github.com/users/RestKit",
        "html_url": "https://github.com/RestKit",
        "followers_url": "https://api.github.com/users/RestKit/followers",
        "following_url": "https://api.github.com/users/RestKit/following{/other_user}",
        "gists_url": "https://api.github.com/users/RestKit/gists{/gist_id}",
        "starred_url": "https://api.github.com/users/RestKit/starred{/owner}{/repo}",
        "subscriptions_url": "https://api.github.com/users/RestKit/subscriptions",
        "organizations_url": "https://api.github.com/users/RestKit/orgs",
        "repos_url": "https://api.github.com/users/RestKit/repos",
        "events_url": "https://api.github.com/users/RestKit/events{/privacy}",
        "received_events_url": "https://api.github.com/users/RestKit/received_events",
        "type": "Organization",
        "site_admin": false
      },
      "private": false,
      "html_url": "https://github.com/RestKit/RestKit",
      "description": "RestKit is a framework for consuming and modeling RESTful web resources on iOS and OS X",
      "fork": false,
      "url": "https://api.github.com/repos/RestKit/RestKit",
      "forks_url": "https://api.github.com/repos/RestKit/RestKit/forks",
      "keys_url": "https://api.github.com/repos/RestKit/RestKit/keys{/key_id}",
      "collaborators_url": "https://api.github.com/repos/RestKit/RestKit/collaborators{/collaborator}",
      "teams_url": "https://api.github.com/repos/RestKit/RestKit/teams",
      "hooks_url": "https://api.github.com/repos/RestKit/RestKit/hooks",
      "issue_events_url": "https://api.github.com/repos/RestKit/RestKit/issues/events{/number}",
      "events_url": "https://api.github.com/repos/RestKit/RestKit/events",
      "assignees_url": "https://api.github.com/repos/RestKit/RestKit/assignees{/user}",
      "branches_url": "https://api.github.com/repos/RestKit/RestKit/branches{/branch}",
      "tags_url": "https://api.github.com/repos/RestKit/RestKit/tags",
      "blobs_url": "https://api.github.com/repos/RestKit/RestKit/git/blobs{/sha}",
      "git_tags_url": "https://api.github.com/repos/RestKit/RestKit/git/tags{/sha}",
      "git_refs_url": "https://api.github.com/repos/RestKit/RestKit/git/refs{/sha}",
      "trees_url": "https://api.github.com/repos/RestKit/RestKit/git/trees{/sha}",
      "statuses_url": "https://api.github.com/repos/RestKit/RestKit/statuses/{sha}",
      "languages_url": "https://api.github.com/repos/RestKit/RestKit/languages",
      "stargazers_url": "https://api.github.com/repos/RestKit/RestKit/stargazers",
      "contributors_url": "https://api.github.com/repos/RestKit/RestKit/contributors",
      "subscribers_url": "https://api.github.com/repos/RestKit/RestKit/subscribers",
      "subscription_url": "https://api.github.com/repos/RestKit/RestKit/subscription",
      "commits_url": "https://api.github.com/repos/RestKit/RestKit/commits{/sha}",
      "git_commits_url": "https://api.github.com/repos/RestKit/RestKit/git/commits{/sha}",
      "comments_url": "https://api.github.com/repos/RestKit/RestKit/comments{/number}",
      "issue_comment_url": "https://api.github.com/repos/RestKit/RestKit/issues/comments{/number}",
      "contents_url": "https://api.github.com/repos/RestKit/RestKit/contents/{+path}",
      "compare_url": "https://api.github.com/repos/RestKit/RestKit/compare/{base}...{head}",
      "merges_url": "https://api.github.com/repos/RestKit/RestKit/merges",
      "archive_url": "https://api.github.com/repos/RestKit/RestKit/{archive_format}{/ref}",
      "downloads_url": "https://api.github.com/repos/RestKit/RestKit/downloads",
      "issues_url": "https://api.github.com/repos/RestKit/RestKit/issues{/number}",
      "pulls_url": "https://api.github.com/repos/RestKit/RestKit/pulls{/number}",
      "milestones_url": "https://api.github.com/repos/RestKit/RestKit/milestones{/number}",
      "notifications_url": "https://api.github.com/repos/RestKit/RestKit/notifications{?since,all,participating}",
      "labels_url": "https://api.github.com/repos/RestKit/RestKit/labels{/name}",
      "releases_url": "https://api.github.com/repos/RestKit/RestKit/releases{/id}",
      "created_at": "2010-02-09T01:14:06Z",
      "updated_at": "2015-05-09T14:29:01Z",
      "pushed_at": "2015-05-01T13:40:49Z",
      "git_url": "git://github.com/RestKit/RestKit.git",
      "ssh_url": "git@github.com:RestKit/RestKit.git",
      "clone_url": "https://github.com/RestKit/RestKit.git",
      "svn_url": "https://github.com/RestKit/RestKit",
      "homepage": "",
      "size": 68629,
      "stargazers_count": 7985,
      "watchers_count": 7985,
      "language": "Objective-C",
      "has_issues": true,
      "has_downloads": true,
      "has_wiki": true,
      "has_pages": false,
      "forks_count": 1867,
      "mirror_url": null,
      "open_issues_count": 223,
      "forks": 1867,
      "open_issues": 223,
      "watchers": 7985,
      "default_branch": "development",
      "score": 1.0
    }
  ]
}